README.md
setup.py
bin/xkeysnail
xkeysnail/__init__.py
xkeysnail/info.py
xkeysnail/input.py
xkeysnail/key.py
xkeysnail/output.py
xkeysnail/transform.py
xkeysnail.egg-info/PKG-INFO
xkeysnail.egg-info/SOURCES.txt
xkeysnail.egg-info/dependency_links.txt
xkeysnail.egg-info/requires.txt
xkeysnail.egg-info/top_level.txt