Metadata-Version: 1.0
Name: xkeysnail
Version: 0.0.8
Summary: Yet another keyboard remapping tool for X environment.
Home-page: https://github.com/mooz/xkeysnail
Author: Masafumi Oyamada
Author-email: UNKNOWN
License: GPL
Platform: UNKNOWN
